a4agro_vegetation_index_calculation/__init__.py
a4agro_vegetation_index_calculation/colorsmaps.py
a4agro_vegetation_index_calculation/constants.py
a4agro_vegetation_index_calculation/exceptions.py
a4agro_vegetation_index_calculation/index_calculation.py
a4agro_vegetation_index_calculation/plot_generation.py
a4agro_vegetation_index_calculation-1.5.0.dist-info/METADATA
a4agro_vegetation_index_calculation-1.5.0.dist-info/WHEEL
a4agro_vegetation_index_calculation-1.5.0.dist-info/top_level.txt
a4agro_vegetation_index_calculation-1.5.0.dist-info/RECORD
