Metadata-Version: 2.2
Name: a4agro_vegetation_index_calculation
Version: 1.5.0
Summary: This is a package for a4agro vegetation index calculation and generation of figures
Author: Jesus Aguirre
Author-email: jaguirre@a4agro.com
Keywords: vegetation,index,a4agro
Classifier: Development Status :: 3 - Alpha
Classifier: Intended Audience :: Developers
Classifier: Topic :: Software Development :: Build Tools
Classifier: License :: OSI Approved :: MIT License
Classifier: Programming Language :: Python :: 3.12
Requires-Dist: numpy
Requires-Dist: matplotlib
Requires-Dist: rasterio
Requires-Dist: scipy
Requires-Dist: PyQt6
Requires-Dist: scikit-image
Dynamic: author
Dynamic: author-email
Dynamic: classifier
Dynamic: description
Dynamic: keywords
Dynamic: requires-dist
Dynamic: summary
